README
setup.cfg
setup.py
Bops.egg-info/PKG-INFO
Bops.egg-info/SOURCES.txt
Bops.egg-info/dependency_links.txt
Bops.egg-info/top_level.txt
bops/__init__.py
bops/bop.py
bops/exceptions.py
bops/ordereddict.py
bops.egg-info/SOURCES.txt
examples/mr_perf_testing.py
examples/simple.py
examples/test_data_gen.py
examples/word_count.py