Metadata-Version: 1.1
Name: bops
Version: 0.5
Summary: A non-distributed numpy-based analysis module focusing on the manipulation,                     grouping and filtering of data from various sources.                     Bops also has map-reduce functionality.
Home-page: http://packages.python.org/bops
Author: Max Franks
Author-email: eliquious@gmail.com
License: MIT
Keywords: mapreduce data analysis map-reduce
Platform: UNKNOWN
Classifier: Development Status :: 4 - Beta
Classifier: Natural Language :: English
Classifier: Topic :: Scientific/Engineering :: Information Analysis
Classifier: License :: OSI Approved :: MIT License
Requires: numpy
